[
    {
        "FileName": "A-Train HX (EU).iso",
        "Size": "7.30 GB",
        "DownloadLink": "https://archive.org/download/CentralArquivista-XBOX360-part2/A-Train HX (EU).iso"
    },
    {
        "FileName": "Assassins Creed 3 (EU - AS) - Disc-1.iso",
        "Size": "8.14 GB",
        "DownloadLink": "https://archive.org/download/CentralArquivista-XBOX360-part2/Assassins Creed 3 (EU - AS) - Disc-1.iso"
    },
    {
        "FileName": "Assassins Creed 3 (EU - AS) - Disc-2.iso",
        "Size": "8.14 GB",
        "DownloadLink": "https://archive.org/download/CentralArquivista-XBOX360-part2/Assassins Creed 3 (EU - AS) - Disc-2.iso"
    },
    {
        "FileName": "Assassins Creed 3 (EU) (Rev-1) - Disc-1.iso",
        "Size": "8.14 GB",
        "DownloadLink": "https://archive.org/download/CentralArquivista-XBOX360-part2/Assassins Creed 3 (EU) (Rev-1) - Disc-1.iso"
    },
    {
        "FileName": "Assassins Creed 3 (EU) (Rev-1) - Disc-2.iso",
        "Size": "8.14 GB",
        "DownloadLink": "https://archive.org/download/CentralArquivista-XBOX360-part2/Assassins Creed 3 (EU) (Rev-1) - Disc-2.iso"
    },
    {
        "FileName": "Assassins Creed 3 (EU) - Disc-1.iso",
        "Size": "8.14 GB",
        "DownloadLink": "https://archive.org/download/CentralArquivista-XBOX360-part2/Assassins Creed 3 (EU) - Disc-1.iso"
    },
    {
        "FileName": "Assassins Creed 3 (EU) - Disc-2.iso",
        "Size": "8.14 GB",
        "DownloadLink": "https://archive.org/download/CentralArquivista-XBOX360-part2/Assassins Creed 3 (EU) - Disc-2.iso"
    },
    {
        "FileName": "Assassins Creed 3 (JP - KO) - Disc-1.iso",
        "Size": "8.14 GB",
        "DownloadLink": "https://archive.org/download/CentralArquivista-XBOX360-part2/Assassins Creed 3 (JP - KO) - Disc-1.iso"
    },
    {
        "FileName": "Assassins Creed 3 (JP - KO) - Disc-2.iso",
        "Size": "8.14 GB",
        "DownloadLink": "https://archive.org/download/CentralArquivista-XBOX360-part2/Assassins Creed 3 (JP - KO) - Disc-2.iso"
    },
    {
        "FileName": "Assassins Creed 3 (US) (Multiplayer) (Rev-1) - Disc-2.iso",
        "Size": "8.14 GB",
        "DownloadLink": "https://archive.org/download/CentralArquivista-XBOX360-part2/Assassins Creed 3 (US) (Multiplayer) (Rev-1) - Disc-2.iso"
    },
    {
        "FileName": "Assassins Creed 3 (US) (Multiplayer) - Disc-2.iso",
        "Size": "8.14 GB",
        "DownloadLink": "https://archive.org/download/CentralArquivista-XBOX360-part2/Assassins Creed 3 (US) (Multiplayer) - Disc-2.iso"
    },
    {
        "FileName": "Assassins Creed 3 (US) (Single-player) (Rev-1) - Disc-1.iso",
        "Size": "8.14 GB",
        "DownloadLink": "https://archive.org/download/CentralArquivista-XBOX360-part2/Assassins Creed 3 (US) (Single-player) (Rev-1) - Disc-1.iso"
    },
    {
        "FileName": "Assassins Creed 3 (US) (Single-player) - Disc-1.iso",
        "Size": "8.14 GB",
        "DownloadLink": "https://archive.org/download/CentralArquivista-XBOX360-part2/Assassins Creed 3 (US) (Single-player) - Disc-1.iso"
    },
    {
        "FileName": "Assassins Creed 4 - Black Flag (EU) (Multiplayer) - Disc-2.iso",
        "Size": "8.14 GB",
        "DownloadLink": "https://archive.org/download/CentralArquivista-XBOX360-part2/Assassins Creed 4 - Black Flag (EU) (Multiplayer) - Disc-2.iso"
    },
    {
        "FileName": "Assassins Creed 4 - Black Flag (EU) - Disc-1.iso",
        "Size": "8.14 GB",
        "DownloadLink": "https://archive.org/download/CentralArquivista-XBOX360-part2/Assassins Creed 4 - Black Flag (EU) - Disc-1.iso"
    },
    {
        "FileName": "Assassins Creed 4 - Black Flag (JP - KO) (Multiplayer) - Disc-2.iso",
        "Size": "8.14 GB",
        "DownloadLink": "https://archive.org/download/CentralArquivista-XBOX360-part2/Assassins Creed 4 - Black Flag (JP - KO) (Multiplayer) - Disc-2.iso"
    },
    {
        "FileName": "Assassins Creed 4 - Black Flag (JP - KO) - Disc-1.iso",
        "Size": "8.14 GB",
        "DownloadLink": "https://archive.org/download/CentralArquivista-XBOX360-part2/Assassins Creed 4 - Black Flag (JP - KO) - Disc-1.iso"
    },
    {
        "FileName": "Assassins Creed 4 - Black Flag (UK - AU) - Disc-1.iso",
        "Size": "8.14 GB",
        "DownloadLink": "https://archive.org/download/CentralArquivista-XBOX360-part2/Assassins Creed 4 - Black Flag (UK - AU) - Disc-1.iso"
    },
    {
        "FileName": "Assassins Creed 4 - Black Flag (UK - AU) - Disc-2.iso",
        "Size": "8.14 GB",
        "DownloadLink": "https://archive.org/download/CentralArquivista-XBOX360-part2/Assassins Creed 4 - Black Flag (UK - AU) - Disc-2.iso"
    },
    {
        "FileName": "Assassins Creed 4 - Black Flag (US - EU) - Disc-1.iso",
        "Size": "8.14 GB",
        "DownloadLink": "https://archive.org/download/CentralArquivista-XBOX360-part2/Assassins Creed 4 - Black Flag (US - EU) - Disc-1.iso"
    },
    {
        "FileName": "Assassins Creed 4 - Black Flag (US - EU) - Disc-2.iso",
        "Size": "8.14 GB",
        "DownloadLink": "https://archive.org/download/CentralArquivista-XBOX360-part2/Assassins Creed 4 - Black Flag (US - EU) - Disc-2.iso"
    },
    {
        "FileName": "Asterix at the Olympic Games (CA).iso",
        "Size": "7.30 GB",
        "DownloadLink": "https://archive.org/download/CentralArquivista-XBOX360-part2/Asterix at the Olympic Games (CA).iso"
    },
    {
        "FileName": "Asuras Wrath (WR).iso",
        "Size": "8.14 GB",
        "DownloadLink": "https://archive.org/download/CentralArquivista-XBOX360-part2/Asuras Wrath (WR).iso"
    },
    {
        "FileName": "Atsumare! Pinata (JP).iso",
        "Size": "7.30 GB",
        "DownloadLink": "https://archive.org/download/CentralArquivista-XBOX360-part2/Atsumare! Pinata (JP).iso"
    },
    {
        "FileName": "Attack of the Movies 3-D (US).iso",
        "Size": "7.30 GB",
        "DownloadLink": "https://archive.org/download/CentralArquivista-XBOX360-part2/Attack of the Movies 3-D (US).iso"
    },
    {
        "FileName": "Autobahn Polizei (US).iso",
        "Size": "7.30 GB",
        "DownloadLink": "https://archive.org/download/CentralArquivista-XBOX360-part2/Autobahn Polizei (US).iso"
    },
    {
        "FileName": "Back to the Future - The Game - 30th Anniversary Edition (US).iso",
        "Size": "7.30 GB",
        "DownloadLink": "https://archive.org/download/CentralArquivista-XBOX360-part2/Back to the Future - The Game - 30th Anniversary Edition (US).iso"
    },
    {
        "FileName": "Backbreaker (US - EU).iso",
        "Size": "7.30 GB",
        "DownloadLink": "https://archive.org/download/CentralArquivista-XBOX360-part2/Backbreaker (US - EU).iso"
    },
    {
        "FileName": "Backyard Sports - Rookie Rush (US).iso",
        "Size": "7.30 GB",
        "DownloadLink": "https://archive.org/download/CentralArquivista-XBOX360-part2/Backyard Sports - Rookie Rush (US).iso"
    },
    {
        "FileName": "Backyard Sports - Sandlot Sluggers (US).iso",
        "Size": "7.30 GB",
        "DownloadLink": "https://archive.org/download/CentralArquivista-XBOX360-part2/Backyard Sports - Sandlot Sluggers (US).iso"
    },
    {
        "FileName": "Baja - Edge of Control (EU).iso",
        "Size": "7.30 GB",
        "DownloadLink": "https://archive.org/download/CentralArquivista-XBOX360-part2/Baja - Edge of Control (EU).iso"
    },
    {
        "FileName": "Baja - Edge of Control (US).iso",
        "Size": "7.30 GB",
        "DownloadLink": "https://archive.org/download/CentralArquivista-XBOX360-part2/Baja - Edge of Control (US).iso"
    },
    {
        "FileName": "Bakugan - Battle Brawlers (US).iso",
        "Size": "7.30 GB",
        "DownloadLink": "https://archive.org/download/CentralArquivista-XBOX360-part2/Bakugan - Battle Brawlers (US).iso"
    },
    {
        "FileName": "Bakugan - Defenders of the Core (US).iso",
        "Size": "7.30 GB",
        "DownloadLink": "https://archive.org/download/CentralArquivista-XBOX360-part2/Bakugan - Defenders of the Core (US).iso"
    },
    {
        "FileName": "Band Hero (US - EU).iso",
        "Size": "7.30 GB",
        "DownloadLink": "https://archive.org/download/CentralArquivista-XBOX360-part2/Band Hero (US - EU).iso"
    },
    {
        "FileName": "BandFuse - Rock Legends (US).iso",
        "Size": "7.30 GB",
        "DownloadLink": "https://archive.org/download/CentralArquivista-XBOX360-part2/BandFuse - Rock Legends (US).iso"
    },
    {
        "FileName": "Banjo-Kazooie - Nuts and Bolts (EU).iso",
        "Size": "7.30 GB",
        "DownloadLink": "https://archive.org/download/CentralArquivista-XBOX360-part2/Banjo-Kazooie - Nuts and Bolts (EU).iso"
    },
    {
        "FileName": "Banjo-Kazooie - Nuts and Bolts (JP).iso",
        "Size": "7.30 GB",
        "DownloadLink": "https://archive.org/download/CentralArquivista-XBOX360-part2/Banjo-Kazooie - Nuts and Bolts (JP).iso"
    },
    {
        "FileName": "Banjo-Kazooie - Nuts and Bolts (US).iso",
        "Size": "7.30 GB",
        "DownloadLink": "https://archive.org/download/CentralArquivista-XBOX360-part2/Banjo-Kazooie - Nuts and Bolts (US).iso"
    },
    {
        "FileName": "Barbie and Her Sisters - Puppy Rescue (US).iso",
        "Size": "7.30 GB",
        "DownloadLink": "https://archive.org/download/CentralArquivista-XBOX360-part2/Barbie and Her Sisters - Puppy Rescue (US).iso"
    },
    {
        "FileName": "Bass Pro Shops - The Hunt (US).iso",
        "Size": "7.30 GB",
        "DownloadLink": "https://archive.org/download/CentralArquivista-XBOX360-part2/Bass Pro Shops - The Hunt (US).iso"
    },
    {
        "FileName": "Bass Pro Shops - The Strike (US).iso",
        "Size": "7.30 GB",
        "DownloadLink": "https://archive.org/download/CentralArquivista-XBOX360-part2/Bass Pro Shops - The Strike (US).iso"
    },
    {
        "FileName": "Batman - Arkham Asylum (JP).iso",
        "Size": "7.30 GB",
        "DownloadLink": "https://archive.org/download/CentralArquivista-XBOX360-part2/Batman - Arkham Asylum (JP).iso"
    },
    {
        "FileName": "Batman - Arkham Asylum (US - EU).iso",
        "Size": "7.30 GB",
        "DownloadLink": "https://archive.org/download/CentralArquivista-XBOX360-part2/Batman - Arkham Asylum (US - EU).iso"
    },
    {
        "FileName": "Batman - Arkham Asylum - Game of the Year Edition (EU).iso",
        "Size": "7.30 GB",
        "DownloadLink": "https://archive.org/download/CentralArquivista-XBOX360-part2/Batman - Arkham Asylum - Game of the Year Edition (EU).iso"
    },
    {
        "FileName": "Batman - Arkham Asylum - Game of the Year Edition (US).iso",
        "Size": "7.30 GB",
        "DownloadLink": "https://archive.org/download/CentralArquivista-XBOX360-part2/Batman - Arkham Asylum - Game of the Year Edition (US).iso"
    },
    {
        "FileName": "Batman - Arkham City (WR).iso",
        "Size": "8.14 GB",
        "DownloadLink": "https://archive.org/download/CentralArquivista-XBOX360-part2/Batman - Arkham City (WR).iso"
    },
    {
        "FileName": "Batman - Arkham City - Game of the Year Edition (US - EU) - Disc-1.iso",
        "Size": "8.14 GB",
        "DownloadLink": "https://archive.org/download/CentralArquivista-XBOX360-part2/Batman - Arkham City - Game of the Year Edition (US - EU) - Disc-1.iso"
    },
    {
        "FileName": "Batman - Arkham City - Game of the Year Edition (US - EU) - Disc-2.iso",
        "Size": "8.14 GB",
        "DownloadLink": "https://archive.org/download/CentralArquivista-XBOX360-part2/Batman - Arkham City - Game of the Year Edition (US - EU) - Disc-2.iso"
    },
    {
        "FileName": "Batman - Arkham Origins (BR) - Disc-1.iso",
        "Size": "8.14 GB",
        "DownloadLink": "https://archive.org/download/CentralArquivista-XBOX360-part2/Batman - Arkham Origins (BR) - Disc-1.iso"
    },
    {
        "FileName": "Batman - Arkham Origins (BR) - Disc-2.iso",
        "Size": "8.14 GB",
        "DownloadLink": "https://archive.org/download/CentralArquivista-XBOX360-part2/Batman - Arkham Origins (BR) - Disc-2.iso"
    },
    {
        "FileName": "Batman - Arkham Origins (US - EU) - Disc-1.iso",
        "Size": "8.14 GB",
        "DownloadLink": "https://archive.org/download/CentralArquivista-XBOX360-part2/Batman - Arkham Origins (US - EU) - Disc-1.iso"
    },
    {
        "FileName": "Batman - Arkham Origins (US - EU) - Disc-2.iso",
        "Size": "8.14 GB",
        "DownloadLink": "https://archive.org/download/CentralArquivista-XBOX360-part2/Batman - Arkham Origins (US - EU) - Disc-2.iso"
    },
    {
        "FileName": "Batman - The Telltale Series (US).iso",
        "Size": "7.30 GB",
        "DownloadLink": "https://archive.org/download/CentralArquivista-XBOX360-part2/Batman - The Telltale Series (US).iso"
    },
    {
        "FileName": "Battle Fantasia (EU).iso",
        "Size": "7.30 GB",
        "DownloadLink": "https://archive.org/download/CentralArquivista-XBOX360-part2/Battle Fantasia (EU).iso"
    },
    {
        "FileName": "Battle Fantasia (JP).iso",
        "Size": "7.30 GB",
        "DownloadLink": "https://archive.org/download/CentralArquivista-XBOX360-part2/Battle Fantasia (JP).iso"
    },
    {
        "FileName": "Battle Fantasia (US).iso",
        "Size": "7.30 GB",
        "DownloadLink": "https://archive.org/download/CentralArquivista-XBOX360-part2/Battle Fantasia (US).iso"
    },
    {
        "FileName": "Battle vs. Chess (EU).iso",
        "Size": "7.30 GB",
        "DownloadLink": "https://archive.org/download/CentralArquivista-XBOX360-part2/Battle vs. Chess (EU).iso"
    },
    {
        "FileName": "Battlefield - Bad Company (EU) (Gold Edition).iso",
        "Size": "7.30 GB",
        "DownloadLink": "https://archive.org/download/CentralArquivista-XBOX360-part2/Battlefield - Bad Company (EU) (Gold Edition).iso"
    },
    {
        "FileName": "Battlefield - Bad Company (EU).iso",
        "Size": "7.30 GB",
        "DownloadLink": "https://archive.org/download/CentralArquivista-XBOX360-part2/Battlefield - Bad Company (EU).iso"
    },
    {
        "FileName": "Battlefield - Bad Company (JP).iso",
        "Size": "7.30 GB",
        "DownloadLink": "https://archive.org/download/CentralArquivista-XBOX360-part2/Battlefield - Bad Company (JP).iso"
    },
    {
        "FileName": "Battlefield - Bad Company (US) (Gold Edition).iso",
        "Size": "7.30 GB",
        "DownloadLink": "https://archive.org/download/CentralArquivista-XBOX360-part2/Battlefield - Bad Company (US) (Gold Edition).iso"
    },
    {
        "FileName": "Battlefield - Bad Company (US).iso",
        "Size": "7.30 GB",
        "DownloadLink": "https://archive.org/download/CentralArquivista-XBOX360-part2/Battlefield - Bad Company (US).iso"
    },
    {
        "FileName": "Battlefield - Bad Company 2 (EU) (Limited Edition).iso",
        "Size": "7.30 GB",
        "DownloadLink": "https://archive.org/download/CentralArquivista-XBOX360-part2/Battlefield - Bad Company 2 (EU) (Limited Edition).iso"
    },
    {
        "FileName": "Battlefield - Bad Company 2 (EU).iso",
        "Size": "7.30 GB",
        "DownloadLink": "https://archive.org/download/CentralArquivista-XBOX360-part2/Battlefield - Bad Company 2 (EU).iso"
    },
    {
        "FileName": "Battlefield - Bad Company 2 (JP).iso",
        "Size": "7.30 GB",
        "DownloadLink": "https://archive.org/download/CentralArquivista-XBOX360-part2/Battlefield - Bad Company 2 (JP).iso"
    },
    {
        "FileName": "Battlefield - Bad Company 2 (US - KR)).iso",
        "Size": "7.30 GB",
        "DownloadLink": "https://archive.org/download/CentralArquivista-XBOX360-part2/Battlefield - Bad Company 2 (US - KR)).iso"
    },
    {
        "FileName": "Battlefield - Bad Company 2 (US) (Limited Edition).iso",
        "Size": "7.30 GB",
        "DownloadLink": "https://archive.org/download/CentralArquivista-XBOX360-part2/Battlefield - Bad Company 2 (US) (Limited Edition).iso"
    },
    {
        "FileName": "Battlefield 2 - Modern Combat (DE).iso",
        "Size": "7.30 GB",
        "DownloadLink": "https://archive.org/download/CentralArquivista-XBOX360-part2/Battlefield 2 - Modern Combat (DE).iso"
    },
    {
        "FileName": "Battlefield 2 - Modern Combat (ES).iso",
        "Size": "7.30 GB",
        "DownloadLink": "https://archive.org/download/CentralArquivista-XBOX360-part2/Battlefield 2 - Modern Combat (ES).iso"
    },
    {
        "FileName": "Battlefield 2 - Modern Combat (EU).iso",
        "Size": "7.30 GB",
        "DownloadLink": "https://archive.org/download/CentralArquivista-XBOX360-part2/Battlefield 2 - Modern Combat (EU).iso"
    },
    {
        "FileName": "Battlefield 2 - Modern Combat (IT).iso",
        "Size": "7.30 GB",
        "DownloadLink": "https://archive.org/download/CentralArquivista-XBOX360-part2/Battlefield 2 - Modern Combat (IT).iso"
    },
    {
        "FileName": "Battlefield 2 - Modern Combat (JP).iso",
        "Size": "7.30 GB",
        "DownloadLink": "https://archive.org/download/CentralArquivista-XBOX360-part2/Battlefield 2 - Modern Combat (JP).iso"
    },
    {
        "FileName": "Battlefield 2 - Modern Combat (US).iso",
        "Size": "7.30 GB",
        "DownloadLink": "https://archive.org/download/CentralArquivista-XBOX360-part2/Battlefield 2 - Modern Combat (US).iso"
    },
    {
        "FileName": "Battlefield 3 (JP - KR) (Multiplay-COOP) - Disc-1.iso",
        "Size": "8.14 GB",
        "DownloadLink": "https://archive.org/download/CentralArquivista-XBOX360-part2/Battlefield 3 (JP - KR) (Multiplay-COOP) - Disc-1.iso"
    },
    {
        "FileName": "Battlefield 3 (JP - KR) (Single-Play) - Disc-2.iso",
        "Size": "8.14 GB",
        "DownloadLink": "https://archive.org/download/CentralArquivista-XBOX360-part2/Battlefield 3 (JP - KR) (Single-Play) - Disc-2.iso"
    },
    {
        "FileName": "Battlefield 3 (US - EU) (Multiplayer-Co-Op) - Disc-1.iso",
        "Size": "8.14 GB",
        "DownloadLink": "https://archive.org/download/CentralArquivista-XBOX360-part2/Battlefield 3 (US - EU) (Multiplayer-Co-Op) - Disc-1.iso"
    },
    {
        "FileName": "Battlefield 3 (US - EU) (Single-Player Campaign) - Disc-2.iso",
        "Size": "8.14 GB",
        "DownloadLink": "https://archive.org/download/CentralArquivista-XBOX360-part2/Battlefield 3 (US - EU) (Single-Player Campaign) - Disc-2.iso"
    },
    {
        "FileName": "Battlefield 4 (JP) - Disc-1.iso",
        "Size": "8.14 GB",
        "DownloadLink": "https://archive.org/download/CentralArquivista-XBOX360-part2/Battlefield 4 (JP) - Disc-1.iso"
    },
    {
        "FileName": "Battlefield 4 (JP) - Disc-2.iso",
        "Size": "8.14 GB",
        "DownloadLink": "https://archive.org/download/CentralArquivista-XBOX360-part2/Battlefield 4 (JP) - Disc-2.iso"
    },
    {
        "FileName": "Battlefield 4 (US - EU) - Disc-1.iso",
        "Size": "8.14 GB",
        "DownloadLink": "https://archive.org/download/CentralArquivista-XBOX360-part2/Battlefield 4 (US - EU) - Disc-1.iso"
    },
    {
        "FileName": "Battlefield 4 (US - EU) - Disc-2.iso",
        "Size": "8.14 GB",
        "DownloadLink": "https://archive.org/download/CentralArquivista-XBOX360-part2/Battlefield 4 (US - EU) - Disc-2.iso"
    },
    {
        "FileName": "Battlefield Hardline (US - EU) (Install-Multiplayer) - Disc-1.iso",
        "Size": "8.14 GB",
        "DownloadLink": "https://archive.org/download/CentralArquivista-XBOX360-part2/Battlefield Hardline (US - EU) (Install-Multiplayer) - Disc-1.iso"
    },
    {
        "FileName": "Battlefield Hardline (US - EU) (Single Player) - Disc-2.iso",
        "Size": "8.14 GB",
        "DownloadLink": "https://archive.org/download/CentralArquivista-XBOX360-part2/Battlefield Hardline (US - EU) (Single Player) - Disc-2.iso"
    },
    {
        "FileName": "Battleship (US).iso",
        "Size": "7.30 GB",
        "DownloadLink": "https://archive.org/download/CentralArquivista-XBOX360-part2/Battleship (US).iso"
    },
    {
        "FileName": "Battlestations - Midway (JP).iso",
        "Size": "7.30 GB",
        "DownloadLink": "https://archive.org/download/CentralArquivista-XBOX360-part2/Battlestations - Midway (JP).iso"
    },
    {
        "FileName": "Battlestations - Midway (US - EU).iso",
        "Size": "7.30 GB",
        "DownloadLink": "https://archive.org/download/CentralArquivista-XBOX360-part2/Battlestations - Midway (US - EU).iso"
    },
    {
        "FileName": "Battlestations - Pacific (US).iso",
        "Size": "7.30 GB",
        "DownloadLink": "https://archive.org/download/CentralArquivista-XBOX360-part2/Battlestations - Pacific (US).iso"
    },
    {
        "FileName": "Bayonetta (JP).iso",
        "Size": "7.30 GB",
        "DownloadLink": "https://archive.org/download/CentralArquivista-XBOX360-part2/Bayonetta (JP).iso"
    },
    {
        "FileName": "Bayonetta (US - EU).iso",
        "Size": "7.30 GB",
        "DownloadLink": "https://archive.org/download/CentralArquivista-XBOX360-part2/Bayonetta (US - EU).iso"
    },
    {
        "FileName": "Beautiful Katamari Damacy (JP - AS).iso",
        "Size": "7.30 GB",
        "DownloadLink": "https://archive.org/download/CentralArquivista-XBOX360-part2/Beautiful Katamari Damacy (JP - AS).iso"
    },
    {
        "FileName": "Beijing 2008 (JP).iso",
        "Size": "7.30 GB",
        "DownloadLink": "https://archive.org/download/CentralArquivista-XBOX360-part2/Beijing 2008 (JP).iso"
    },
    {
        "FileName": "Beijing 2008 (US - EU).iso",
        "Size": "7.30 GB",
        "DownloadLink": "https://archive.org/download/CentralArquivista-XBOX360-part2/Beijing 2008 (US - EU).iso"
    },
    {
        "FileName": "Bejeweled 3 (EU).iso",
        "Size": "7.30 GB",
        "DownloadLink": "https://archive.org/download/CentralArquivista-XBOX360-part2/Bejeweled 3 (EU).iso"
    },
    {
        "FileName": "Bejeweled 3 (US).iso",
        "Size": "7.30 GB",
        "DownloadLink": "https://archive.org/download/CentralArquivista-XBOX360-part2/Bejeweled 3 (US).iso"
    },
    {
        "FileName": "Ben 10 - Alien Force - Vilgax Attacks (US - EU).iso",
        "Size": "7.30 GB",
        "DownloadLink": "https://archive.org/download/CentralArquivista-XBOX360-part2/Ben 10 - Alien Force - Vilgax Attacks (US - EU).iso"
    },
    {
        "FileName": "Ben 10 - Galactic Racing (US - EU).iso",
        "Size": "7.30 GB",
        "DownloadLink": "https://archive.org/download/CentralArquivista-XBOX360-part2/Ben 10 - Galactic Racing (US - EU).iso"
    },
    {
        "FileName": "Ben 10 - Omniverse (US).iso",
        "Size": "7.30 GB",
        "DownloadLink": "https://archive.org/download/CentralArquivista-XBOX360-part2/Ben 10 - Omniverse (US).iso"
    },
    {
        "FileName": "Ben 10 - Omniverse 2 (US - EU).iso",
        "Size": "7.30 GB",
        "DownloadLink": "https://archive.org/download/CentralArquivista-XBOX360-part2/Ben 10 - Omniverse 2 (US - EU).iso"
    },
    {
        "FileName": "Ben 10 - Ultimate Alien - Cosmic Destruction (US).iso",
        "Size": "7.30 GB",
        "DownloadLink": "https://archive.org/download/CentralArquivista-XBOX360-part2/Ben 10 - Ultimate Alien - Cosmic Destruction (US).iso"
    },
    {
        "FileName": "Beowulf - The Game (US - EU).iso",
        "Size": "7.30 GB",
        "DownloadLink": "https://archive.org/download/CentralArquivista-XBOX360-part2/Beowulf - The Game (US - EU).iso"
    },
    {
        "FileName": "007 - Blood Stone (US - EU).iso",
        "Size": "7.30 GB",
        "DownloadLink": "https://archive.org/download/CentralArquivista-XBOX360-part1/007 - Blood Stone (US - EU).iso"
    },
    {
        "FileName": "007 - Ein Quantum Trost (DE).iso",
        "Size": "7.30 GB",
        "DownloadLink": "https://archive.org/download/CentralArquivista-XBOX360-part1/007 - Ein Quantum Trost (DE).iso"
    },
    {
        "FileName": "007 - Legends (US).iso",
        "Size": "8.14 GB",
        "DownloadLink": "https://archive.org/download/CentralArquivista-XBOX360-part1/007 - Legends (US).iso"
    },
    {
        "FileName": "007 - Nagusame no Houshuu (JP).iso",
        "Size": "7.30 GB",
        "DownloadLink": "https://archive.org/download/CentralArquivista-XBOX360-part1/007 - Nagusame no Houshuu (JP).iso"
    },
    {
        "FileName": "007 - Quantum of Solace (ES).iso",
        "Size": "7.30 GB",
        "DownloadLink": "https://archive.org/download/CentralArquivista-XBOX360-part1/007 - Quantum of Solace (ES).iso"
    },
    {
        "FileName": "007 - Quantum of Solace (IT).iso",
        "Size": "7.30 GB",
        "DownloadLink": "https://archive.org/download/CentralArquivista-XBOX360-part1/007 - Quantum of Solace (IT).iso"
    },
    {
        "FileName": "007 - Quantum of Solace (US - EU).iso",
        "Size": "7.30 GB",
        "DownloadLink": "https://archive.org/download/CentralArquivista-XBOX360-part1/007 - Quantum of Solace (US - EU).iso"
    },
    {
        "FileName": "11eyes CrossOver (JP).iso",
        "Size": "7.30 GB",
        "DownloadLink": "https://archive.org/download/CentralArquivista-XBOX360-part1/11eyes CrossOver (JP).iso"
    },
    {
        "FileName": "2010 FIFA World Cup - Minami Africa Taikai (JP).iso",
        "Size": "7.30 GB",
        "DownloadLink": "https://archive.org/download/CentralArquivista-XBOX360-part1/2010 FIFA World Cup - Minami Africa Taikai (JP).iso"
    },
    {
        "FileName": "2010 FIFA World Cup - South Africa (EU) (En,Es,Nl).iso",
        "Size": "7.30 GB",
        "DownloadLink": "https://archive.org/download/CentralArquivista-XBOX360-part1/2010 FIFA World Cup - South Africa (EU) (En,Es,Nl).iso"
    },
    {
        "FileName": "2010 FIFA World Cup - South Africa (EU) (Fr,De,It).iso",
        "Size": "7.30 GB",
        "DownloadLink": "https://archive.org/download/CentralArquivista-XBOX360-part1/2010 FIFA World Cup - South Africa (EU) (Fr,De,It).iso"
    },
    {
        "FileName": "2010 FIFA World Cup - South Africa (US - AS).iso",
        "Size": "7.30 GB",
        "DownloadLink": "https://archive.org/download/CentralArquivista-XBOX360-part1/2010 FIFA World Cup - South Africa (US - AS).iso"
    },
    {
        "FileName": "2014 FIFA World Cup - Brazil (EU) (En,De,It).iso",
        "Size": "8.14 GB",
        "DownloadLink": "https://archive.org/download/CentralArquivista-XBOX360-part1/2014 FIFA World Cup - Brazil (EU) (En,De,It).iso"
    },
    {
        "FileName": "2014 FIFA World Cup - Brazil (EU) (Fr,Es,Nl).iso",
        "Size": "8.14 GB",
        "DownloadLink": "https://archive.org/download/CentralArquivista-XBOX360-part1/2014 FIFA World Cup - Brazil (EU) (Fr,Es,Nl).iso"
    },
    {
        "FileName": "2014 FIFA World Cup - Brazil (JP).iso",
        "Size": "8.14 GB",
        "DownloadLink": "https://archive.org/download/CentralArquivista-XBOX360-part1/2014 FIFA World Cup - Brazil (JP).iso"
    },
    {
        "FileName": "2014 FIFA World Cup - Brazil (US).iso",
        "Size": "8.14 GB",
        "DownloadLink": "https://archive.org/download/CentralArquivista-XBOX360-part1/2014 FIFA World Cup - Brazil (US).iso"
    },
    {
        "FileName": "50 Cent - Blood on the Sand (JP).iso",
        "Size": "7.30 GB",
        "DownloadLink": "https://archive.org/download/CentralArquivista-XBOX360-part1/50 Cent - Blood on the Sand (JP).iso"
    },
    {
        "FileName": "50 Cent - Blood on the Sand (US - EU).iso",
        "Size": "7.30 GB",
        "DownloadLink": "https://archive.org/download/CentralArquivista-XBOX360-part1/50 Cent - Blood on the Sand (US - EU).iso"
    },
    {
        "FileName": "A Ressha de Ikou HX (JP).iso",
        "Size": "7.30 GB",
        "DownloadLink": "https://archive.org/download/CentralArquivista-XBOX360-part1/A Ressha de Ikou HX (JP).iso"
    },
    {
        "FileName": "ABC Wipeout 3 (US).iso",
        "Size": "7.30 GB",
        "DownloadLink": "https://archive.org/download/CentralArquivista-XBOX360-part1/ABC Wipeout 3 (US).iso"
    },
    {
        "FileName": "AC-DC Live - Rock Band (EU).iso",
        "Size": "7.30 GB",
        "DownloadLink": "https://archive.org/download/CentralArquivista-XBOX360-part1/AC-DC Live - Rock Band (EU).iso"
    },
    {
        "FileName": "AC-DC Live - Rock Band Track Pack (US).iso",
        "Size": "7.30 GB",
        "DownloadLink": "https://archive.org/download/CentralArquivista-XBOX360-part1/AC-DC Live - Rock Band Track Pack (US).iso"
    },
    {
        "FileName": "AFL Live (AU).iso",
        "Size": "7.30 GB",
        "DownloadLink": "https://archive.org/download/CentralArquivista-XBOX360-part1/AFL Live (AU).iso"
    },
    {
        "FileName": "AFL Live 2 (AU).iso",
        "Size": "7.30 GB",
        "DownloadLink": "https://archive.org/download/CentralArquivista-XBOX360-part1/AFL Live 2 (AU).iso"
    },
    {
        "FileName": "Absolute - Blazing Infinity (JP).iso",
        "Size": "7.30 GB",
        "DownloadLink": "https://archive.org/download/CentralArquivista-XBOX360-part1/Absolute - Blazing Infinity (JP).iso"
    },
    {
        "FileName": "Ace Combat - Assault Horizon (EU).iso",
        "Size": "8.14 GB",
        "DownloadLink": "https://archive.org/download/CentralArquivista-XBOX360-part1/Ace Combat - Assault Horizon (EU).iso"
    },
    {
        "FileName": "Ace Combat - Assault Horizon (JP).iso",
        "Size": "8.14 GB",
        "DownloadLink": "https://archive.org/download/CentralArquivista-XBOX360-part1/Ace Combat - Assault Horizon (JP).iso"
    },
    {
        "FileName": "Ace Combat - Assault Horizon (US).iso",
        "Size": "8.14 GB",
        "DownloadLink": "https://archive.org/download/CentralArquivista-XBOX360-part1/Ace Combat - Assault Horizon (US).iso"
    },
    {
        "FileName": "Ace Combat 6 - Fires of Liberation (EU)(Rev-1).iso",
        "Size": "7.30 GB",
        "DownloadLink": "https://archive.org/download/CentralArquivista-XBOX360-part1/Ace Combat 6 - Fires of Liberation (EU)(Rev-1).iso"
    },
    {
        "FileName": "Ace Combat 6 - Fires of Liberation (EU).iso",
        "Size": "7.30 GB",
        "DownloadLink": "https://archive.org/download/CentralArquivista-XBOX360-part1/Ace Combat 6 - Fires of Liberation (EU).iso"
    },
    {
        "FileName": "Ace Combat 6 - Fires of Liberation (US - JP).iso",
        "Size": "7.30 GB",
        "DownloadLink": "https://archive.org/download/CentralArquivista-XBOX360-part1/Ace Combat 6 - Fires of Liberation (US - JP).iso"
    },
    {
        "FileName": "Ace Combat 6 - Kaihou e no Senka (JP - AS).iso",
        "Size": "7.30 GB",
        "DownloadLink": "https://archive.org/download/CentralArquivista-XBOX360-part1/Ace Combat 6 - Kaihou e no Senka (JP - AS).iso"
    },
    {
        "FileName": "Adidas miCoach (EU) - Disc-1.iso",
        "Size": "8.14 GB",
        "DownloadLink": "https://archive.org/download/CentralArquivista-XBOX360-part1/Adidas miCoach (EU) - Disc-1.iso"
    },
    {
        "FileName": "Adidas miCoach (EU) - Disc-2.iso",
        "Size": "8.14 GB",
        "DownloadLink": "https://archive.org/download/CentralArquivista-XBOX360-part1/Adidas miCoach (EU) - Disc-2.iso"
    },
    {
        "FileName": "Adidas miCoach (US) - Disc-1.iso",
        "Size": "8.14 GB",
        "DownloadLink": "https://archive.org/download/CentralArquivista-XBOX360-part1/Adidas miCoach (US) - Disc-1.iso"
    },
    {
        "FileName": "Adidas miCoach (US) - Disc-2.iso",
        "Size": "8.14 GB",
        "DownloadLink": "https://archive.org/download/CentralArquivista-XBOX360-part1/Adidas miCoach (US) - Disc-2.iso"
    },
    {
        "FileName": "Adrenalin Misfits (US).iso",
        "Size": "7.30 GB",
        "DownloadLink": "https://archive.org/download/CentralArquivista-XBOX360-part1/Adrenalin Misfits (US).iso"
    },
    {
        "FileName": "Adventure Time - Explore the Dungeon Because I Dont Know! (US - EU)).iso",
        "Size": "7.30 GB",
        "DownloadLink": "https://archive.org/download/CentralArquivista-XBOX360-part1/Adventure Time - Explore the Dungeon Because I Dont Know! (US - EU)).iso"
    },
    {
        "FileName": "Adventure Time - Finn and Jake Investigations (US).iso",
        "Size": "7.30 GB",
        "DownloadLink": "https://archive.org/download/CentralArquivista-XBOX360-part1/Adventure Time - Finn and Jake Investigations (US).iso"
    },
    {
        "FileName": "Adventure Time - The Secret of the Nameless Kingdom (US - AU).iso",
        "Size": "7.30 GB",
        "DownloadLink": "https://archive.org/download/CentralArquivista-XBOX360-part1/Adventure Time - The Secret of the Nameless Kingdom (US - AU).iso"
    },
    {
        "FileName": "Afro Samurai (EU).iso",
        "Size": "7.30 GB",
        "DownloadLink": "https://archive.org/download/CentralArquivista-XBOX360-part1/Afro Samurai (EU).iso"
    },
    {
        "FileName": "Afro Samurai (US).iso",
        "Size": "7.30 GB",
        "DownloadLink": "https://archive.org/download/CentralArquivista-XBOX360-part1/Afro Samurai (US).iso"
    },
    {
        "FileName": "Agarest Senki - Re-appearance (JP).iso",
        "Size": "7.30 GB",
        "DownloadLink": "https://archive.org/download/CentralArquivista-XBOX360-part1/Agarest Senki - Re-appearance (JP).iso"
    },
    {
        "FileName": "Agarest Senki Zero - Dawn of War (JP).iso",
        "Size": "7.30 GB",
        "DownloadLink": "https://archive.org/download/CentralArquivista-XBOX360-part1/Agarest Senki Zero - Dawn of War (JP).iso"
    },
    {
        "FileName": "Air Conflicts - Pacific Carriers (EU).iso",
        "Size": "7.30 GB",
        "DownloadLink": "https://archive.org/download/CentralArquivista-XBOX360-part1/Air Conflicts - Pacific Carriers (EU).iso"
    },
    {
        "FileName": "Air Conflicts - Secret Wars (US).iso",
        "Size": "7.30 GB",
        "DownloadLink": "https://archive.org/download/CentralArquivista-XBOX360-part1/Air Conflicts - Secret Wars (US).iso"
    },
    {
        "FileName": "Air Conflicts - Vietnam (US).iso",
        "Size": "7.30 GB",
        "DownloadLink": "https://archive.org/download/CentralArquivista-XBOX360-part1/Air Conflicts - Vietnam (US).iso"
    },
    {
        "FileName": "Akai Katana (US).iso",
        "Size": "7.30 GB",
        "DownloadLink": "https://archive.org/download/CentralArquivista-XBOX360-part1/Akai Katana (US).iso"
    },
    {
        "FileName": "Akai Katana Shin (JP).iso",
        "Size": "7.30 GB",
        "DownloadLink": "https://archive.org/download/CentralArquivista-XBOX360-part1/Akai Katana Shin (JP).iso"
    },
    {
        "FileName": "Akatsuki no Amaneka to Aoi Kyojin - Pashiate Bunmei Kenkyuukai Koubouki (JP).iso",
        "Size": "7.30 GB",
        "DownloadLink": "https://archive.org/download/CentralArquivista-XBOX360-part1/Akatsuki no Amaneka to Aoi Kyojin - Pashiate Bunmei Kenkyuukai Koubouki (JP).iso"
    },
    {
        "FileName": "Alan Wake (US - EU) (Bonus Disc).iso",
        "Size": "7.30 GB",
        "DownloadLink": "https://archive.org/download/CentralArquivista-XBOX360-part1/Alan Wake (US - EU) (Bonus Disc).iso"
    },
    {
        "FileName": "Alan Wake (WR).iso",
        "Size": "7.30 GB",
        "DownloadLink": "https://archive.org/download/CentralArquivista-XBOX360-part1/Alan Wake (WR).iso"
    },
    {
        "FileName": "Alice - Madness Returns (US - EU).iso",
        "Size": "7.30 GB",
        "DownloadLink": "https://archive.org/download/CentralArquivista-XBOX360-part1/Alice - Madness Returns (US - EU).iso"
    },
    {
        "FileName": "Alien - Isolation (US - EU) (Installation Disc) - Disc-1.iso",
        "Size": "7.30 GB",
        "DownloadLink": "https://archive.org/download/CentralArquivista-XBOX360-part1/Alien - Isolation (US - EU) (Installation Disc) - Disc-1.iso"
    },
    {
        "FileName": "Alien - Isolation (US) - Disc-2.iso",
        "Size": "7.30 GB",
        "DownloadLink": "https://archive.org/download/CentralArquivista-XBOX360-part1/Alien - Isolation (US) - Disc-2.iso"
    },
    {
        "FileName": "Alien Breed - Trilogy (EU).iso",
        "Size": "7.30 GB",
        "DownloadLink": "https://archive.org/download/CentralArquivista-XBOX360-part1/Alien Breed - Trilogy (EU).iso"
    },
    {
        "FileName": "Alien vs Predator (US - EU).iso",
        "Size": "7.30 GB",
        "DownloadLink": "https://archive.org/download/CentralArquivista-XBOX360-part1/Alien vs Predator (US - EU).iso"
    },
    {
        "FileName": "Aliens - Colonial Marines (RU).iso",
        "Size": "7.30 GB",
        "DownloadLink": "https://archive.org/download/CentralArquivista-XBOX360-part1/Aliens - Colonial Marines (RU).iso"
    },
    {
        "FileName": "Aliens - Colonial Marines (US - EU).iso",
        "Size": "7.30 GB",
        "DownloadLink": "https://archive.org/download/CentralArquivista-XBOX360-part1/Aliens - Colonial Marines (US - EU).iso"
    },
    {
        "FileName": "Alone in the Dark (US - EU).iso",
        "Size": "7.30 GB",
        "DownloadLink": "https://archive.org/download/CentralArquivista-XBOX360-part1/Alone in the Dark (US - EU).iso"
    },
    {
        "FileName": "Alpha Protocol (US - EU).iso",
        "Size": "7.30 GB",
        "DownloadLink": "https://archive.org/download/CentralArquivista-XBOX360-part1/Alpha Protocol (US - EU).iso"
    },
    {
        "FileName": "Alvin and the Chipmunks - Chipwrecked (US).iso",
        "Size": "7.30 GB",
        "DownloadLink": "https://archive.org/download/CentralArquivista-XBOX360-part1/Alvin and the Chipmunks - Chipwrecked (US).iso"
    },
    {
        "FileName": "America Army - True Soldiers (US).iso",
        "Size": "7.30 GB",
        "DownloadLink": "https://archive.org/download/CentralArquivista-XBOX360-part1/America Army - True Soldiers (US).iso"
    },
    {
        "FileName": "Amped 3 (EU).iso",
        "Size": "7.30 GB",
        "DownloadLink": "https://archive.org/download/CentralArquivista-XBOX360-part1/Amped 3 (EU).iso"
    },
    {
        "FileName": "Amped 3 (US).iso",
        "Size": "7.30 GB",
        "DownloadLink": "https://archive.org/download/CentralArquivista-XBOX360-part1/Amped 3 (US).iso"
    },
    {
        "FileName": "Anarchy Reigns and Max Anarchy (US - JP).iso",
        "Size": "8.14 GB",
        "DownloadLink": "https://archive.org/download/CentralArquivista-XBOX360-part1/Anarchy Reigns and Max Anarchy (US - JP).iso"
    },
    {
        "FileName": "Angry Birds Star Wars (US).iso",
        "Size": "7.30 GB",
        "DownloadLink": "https://archive.org/download/CentralArquivista-XBOX360-part1/Angry Birds Star Wars (US).iso"
    },
    {
        "FileName": "Angry Birds Trilogy (US - EU).iso",
        "Size": "7.30 GB",
        "DownloadLink": "https://archive.org/download/CentralArquivista-XBOX360-part1/Angry Birds Trilogy (US - EU).iso"
    },
    {
        "FileName": "Apache - Air Assault (US).iso",
        "Size": "7.30 GB",
        "DownloadLink": "https://archive.org/download/CentralArquivista-XBOX360-part1/Apache - Air Assault (US).iso"
    },
    {
        "FileName": "Apocalypse - Desire Next (JP).iso",
        "Size": "7.30 GB",
        "DownloadLink": "https://archive.org/download/CentralArquivista-XBOX360-part1/Apocalypse - Desire Next (JP).iso"
    },
    {
        "FileName": "Aquazone - Life Simulator (JP).iso",
        "Size": "7.30 GB",
        "DownloadLink": "https://archive.org/download/CentralArquivista-XBOX360-part1/Aquazone - Life Simulator (JP).iso"
    },
    {
        "FileName": "Arcana Heart 3 (EU).iso",
        "Size": "7.30 GB",
        "DownloadLink": "https://archive.org/download/CentralArquivista-XBOX360-part1/Arcana Heart 3 (EU).iso"
    },
    {
        "FileName": "Arcana Heart 3 (JP).iso",
        "Size": "7.30 GB",
        "DownloadLink": "https://archive.org/download/CentralArquivista-XBOX360-part1/Arcana Heart 3 (JP).iso"
    },
    {
        "FileName": "Arcania - Gothic 4 (JP).iso",
        "Size": "7.30 GB",
        "DownloadLink": "https://archive.org/download/CentralArquivista-XBOX360-part1/Arcania - Gothic 4 (JP).iso"
    },
    {
        "FileName": "Arcania - Gothic 4 (US).iso",
        "Size": "7.30 GB",
        "DownloadLink": "https://archive.org/download/CentralArquivista-XBOX360-part1/Arcania - Gothic 4 (US).iso"
    },
    {
        "FileName": "Arcania - The Complete Tale (EU).iso",
        "Size": "8.14 GB",
        "DownloadLink": "https://archive.org/download/CentralArquivista-XBOX360-part1/Arcania - The Complete Tale (EU).iso"
    },
    {
        "FileName": "Are You Smarter Than a 5th Grader Game Time (US).iso",
        "Size": "7.30 GB",
        "DownloadLink": "https://archive.org/download/CentralArquivista-XBOX360-part1/Are You Smarter Than a 5th Grader Game Time (US).iso"
    },
    {
        "FileName": "Armored Core - For Answer (EU).iso",
        "Size": "7.30 GB",
        "DownloadLink": "https://archive.org/download/CentralArquivista-XBOX360-part1/Armored Core - For Answer (EU).iso"
    },
    {
        "FileName": "Armored Core - For Answer (JP).iso",
        "Size": "7.30 GB",
        "DownloadLink": "https://archive.org/download/CentralArquivista-XBOX360-part1/Armored Core - For Answer (JP).iso"
    },
    {
        "FileName": "Armored Core - For Answer (US).iso",
        "Size": "7.30 GB",
        "DownloadLink": "https://archive.org/download/CentralArquivista-XBOX360-part1/Armored Core - For Answer (US).iso"
    },
    {
        "FileName": "Armored Core - Verdict Day (JP).iso",
        "Size": "7.30 GB",
        "DownloadLink": "https://archive.org/download/CentralArquivista-XBOX360-part1/Armored Core - Verdict Day (JP).iso"
    },
    {
        "FileName": "Armored Core - Verdict Day (US).iso",
        "Size": "7.30 GB",
        "DownloadLink": "https://archive.org/download/CentralArquivista-XBOX360-part1/Armored Core - Verdict Day (US).iso"
    },
    {
        "FileName": "Armored Core 4 (EU).iso",
        "Size": "7.30 GB",
        "DownloadLink": "https://archive.org/download/CentralArquivista-XBOX360-part1/Armored Core 4 (EU).iso"
    },
    {
        "FileName": "Armored Core 4 (JP - KO).iso",
        "Size": "7.30 GB",
        "DownloadLink": "https://archive.org/download/CentralArquivista-XBOX360-part1/Armored Core 4 (JP - KO).iso"
    },
    {
        "FileName": "Armored Core 4 (US).iso",
        "Size": "7.30 GB",
        "DownloadLink": "https://archive.org/download/CentralArquivista-XBOX360-part1/Armored Core 4 (US).iso"
    },
    {
        "FileName": "Armored Core 5 (AS).iso",
        "Size": "7.30 GB",
        "DownloadLink": "https://archive.org/download/CentralArquivista-XBOX360-part1/Armored Core 5 (AS).iso"
    },
    {
        "FileName": "Armored Core 5 (EU).iso",
        "Size": "7.30 GB",
        "DownloadLink": "https://archive.org/download/CentralArquivista-XBOX360-part1/Armored Core 5 (EU).iso"
    },
    {
        "FileName": "Armored Core 5 (JP).iso",
        "Size": "7.30 GB",
        "DownloadLink": "https://archive.org/download/CentralArquivista-XBOX360-part1/Armored Core 5 (JP).iso"
    },
    {
        "FileName": "Armored Core 5 (US).iso",
        "Size": "7.30 GB",
        "DownloadLink": "https://archive.org/download/CentralArquivista-XBOX360-part1/Armored Core 5 (US).iso"
    },
    {
        "FileName": "Army of Two (EU).iso",
        "Size": "7.30 GB",
        "DownloadLink": "https://archive.org/download/CentralArquivista-XBOX360-part1/Army of Two (EU).iso"
    },
    {
        "FileName": "Army of Two (JP).iso",
        "Size": "7.30 GB",
        "DownloadLink": "https://archive.org/download/CentralArquivista-XBOX360-part1/Army of Two (JP).iso"
    },
    {
        "FileName": "Army of Two (KO).iso",
        "Size": "7.30 GB",
        "DownloadLink": "https://archive.org/download/CentralArquivista-XBOX360-part1/Army of Two (KO).iso"
    },
    {
        "FileName": "Army of Two (US).iso",
        "Size": "7.30 GB",
        "DownloadLink": "https://archive.org/download/CentralArquivista-XBOX360-part1/Army of Two (US).iso"
    },
    {
        "FileName": "Army of Two - The 40th Day (JP).iso",
        "Size": "7.30 GB",
        "DownloadLink": "https://archive.org/download/CentralArquivista-XBOX360-part1/Army of Two - The 40th Day (JP).iso"
    },
    {
        "FileName": "Army of Two - The 40th Day (US - AU).iso",
        "Size": "7.30 GB",
        "DownloadLink": "https://archive.org/download/CentralArquivista-XBOX360-part1/Army of Two - The 40th Day (US - AU).iso"
    },
    {
        "FileName": "Army of Two - The Devil Cartel (DE).iso",
        "Size": "8.14 GB",
        "DownloadLink": "https://archive.org/download/CentralArquivista-XBOX360-part1/Army of Two - The Devil Cartel (DE).iso"
    },
    {
        "FileName": "Army of Two - The Devil Cartel (EU).iso",
        "Size": "8.14 GB",
        "DownloadLink": "https://archive.org/download/CentralArquivista-XBOX360-part1/Army of Two - The Devil Cartel (EU).iso"
    },
    {
        "FileName": "Army of Two - The Devil Cartel (US - EU).iso",
        "Size": "8.14 GB",
        "DownloadLink": "https://archive.org/download/CentralArquivista-XBOX360-part1/Army of Two - The Devil Cartel (US - EU).iso"
    },
    {
        "FileName": "Ashes Cricket 2009 (EU).iso",
        "Size": "7.30 GB",
        "DownloadLink": "https://archive.org/download/CentralArquivista-XBOX360-part1/Ashes Cricket 2009 (EU).iso"
    },
    {
        "FileName": "Assassins Creed (JP).iso",
        "Size": "7.30 GB",
        "DownloadLink": "https://archive.org/download/CentralArquivista-XBOX360-part1/Assassins Creed (JP).iso"
    },
    {
        "FileName": "Assassins Creed (PL).iso",
        "Size": "7.30 GB",
        "DownloadLink": "https://archive.org/download/CentralArquivista-XBOX360-part1/Assassins Creed (PL).iso"
    },
    {
        "FileName": "Assassins Creed (US - EU) (Rev-1).iso",
        "Size": "7.30 GB",
        "DownloadLink": "https://archive.org/download/CentralArquivista-XBOX360-part1/Assassins Creed (US - EU) (Rev-1).iso"
    },
    {
        "FileName": "Assassins Creed (US - EU).iso",
        "Size": "7.30 GB",
        "DownloadLink": "https://archive.org/download/CentralArquivista-XBOX360-part1/Assassins Creed (US - EU).iso"
    },
    {
        "FileName": "Assassins Creed - Brotherhood (EU - AS).iso",
        "Size": "7.30 GB",
        "DownloadLink": "https://archive.org/download/CentralArquivista-XBOX360-part1/Assassins Creed - Brotherhood (EU - AS).iso"
    },
    {
        "FileName": "Assassins Creed - Brotherhood (EU).iso",
        "Size": "7.30 GB",
        "DownloadLink": "https://archive.org/download/CentralArquivista-XBOX360-part1/Assassins Creed - Brotherhood (EU).iso"
    },
    {
        "FileName": "Assassins Creed - Brotherhood (JP).iso",
        "Size": "7.30 GB",
        "DownloadLink": "https://archive.org/download/CentralArquivista-XBOX360-part1/Assassins Creed - Brotherhood (JP).iso"
    },
    {
        "FileName": "Assassins Creed - Brotherhood (KO).iso",
        "Size": "7.30 GB",
        "DownloadLink": "https://archive.org/download/CentralArquivista-XBOX360-part1/Assassins Creed - Brotherhood (KO).iso"
    },
    {
        "FileName": "Assassins Creed - Brotherhood (US - EU).iso",
        "Size": "7.30 GB",
        "DownloadLink": "https://archive.org/download/CentralArquivista-XBOX360-part1/Assassins Creed - Brotherhood (US - EU).iso"
    },
    {
        "FileName": "Assassins Creed - Revelations (EU - AU).iso",
        "Size": "8.14 GB",
        "DownloadLink": "https://archive.org/download/CentralArquivista-XBOX360-part1/Assassins Creed - Revelations (EU - AU).iso"
    },
    {
        "FileName": "Assassins Creed - Revelations (JP).iso",
        "Size": "8.14 GB",
        "DownloadLink": "https://archive.org/download/CentralArquivista-XBOX360-part1/Assassins Creed - Revelations (JP).iso"
    },
    {
        "FileName": "Assassins Creed - Revelations (KO).iso",
        "Size": "8.14 GB",
        "DownloadLink": "https://archive.org/download/CentralArquivista-XBOX360-part1/Assassins Creed - Revelations (KO).iso"
    },
    {
        "FileName": "Assassins Creed - Revelations (US - EU).iso",
        "Size": "8.14 GB",
        "DownloadLink": "https://archive.org/download/CentralArquivista-XBOX360-part1/Assassins Creed - Revelations (US - EU).iso"
    },
    {
        "FileName": "Assassins Creed - Rogue (EU).iso",
        "Size": "8.14 GB",
        "DownloadLink": "https://archive.org/download/CentralArquivista-XBOX360-part1/Assassins Creed - Rogue (EU).iso"
    },
    {
        "FileName": "Assassins Creed - Rogue (US - EU).iso",
        "Size": "8.14 GB",
        "DownloadLink": "https://archive.org/download/CentralArquivista-XBOX360-part1/Assassins Creed - Rogue (US - EU).iso"
    },
    {
        "FileName": "Assassins Creed 2 (EU).iso",
        "Size": "7.30 GB",
        "DownloadLink": "https://archive.org/download/CentralArquivista-XBOX360-part1/Assassins Creed 2 (EU).iso"
    },
    {
        "FileName": "Assassins Creed 2 (JP).iso",
        "Size": "7.30 GB",
        "DownloadLink": "https://archive.org/download/CentralArquivista-XBOX360-part1/Assassins Creed 2 (JP).iso"
    },
    {
        "FileName": "Assassins Creed 2 (KO).iso",
        "Size": "7.30 GB",
        "DownloadLink": "https://archive.org/download/CentralArquivista-XBOX360-part1/Assassins Creed 2 (KO).iso"
    },
    {
        "FileName": "Assassins Creed 2 (UK).iso",
        "Size": "7.30 GB",
        "DownloadLink": "https://archive.org/download/CentralArquivista-XBOX360-part1/Assassins Creed 2 (UK).iso"
    },
    {
        "FileName": "Assassins Creed 2 (WR).iso",
        "Size": "7.30 GB",
        "DownloadLink": "https://archive.org/download/CentralArquivista-XBOX360-part1/Assassins Creed 2 (WR).iso"
    },
    {
        "FileName": "Assassins Creed 2 - Game of the Year Edition (EU) (It,Pl,Ru).iso",
        "Size": "7.30 GB",
        "DownloadLink": "https://archive.org/download/CentralArquivista-XBOX360-part1/Assassins Creed 2 - Game of the Year Edition (EU) (It,Pl,Ru).iso"
    },
    {
        "FileName": "Assassins Creed 2 - Game of the Year Edition (EU).iso",
        "Size": "7.30 GB",
        "DownloadLink": "https://archive.org/download/CentralArquivista-XBOX360-part1/Assassins Creed 2 - Game of the Year Edition (EU).iso"
    },
    {
        "FileName": "Assassins Creed 2 - Special Edition (JP).iso",
        "Size": "7.30 GB",
        "DownloadLink": "https://archive.org/download/CentralArquivista-XBOX360-part1/Assassins Creed 2 - Special Edition (JP).iso"
    },
    {
        "FileName": "Assassins Creed 3 (EU) (Rev-1) - Disc-1.iso",
        "Size": "8.14 GB",
        "DownloadLink": "https://archive.org/download/CentralArquivista-XBOX360-part1/Assassins Creed 3 (EU) (Rev-1) - Disc-1.iso"
    },
    {
        "FileName": "Assassins Creed 3 (EU) (Rev-1) - Disc-2.iso",
        "Size": "8.14 GB",
        "DownloadLink": "https://archive.org/download/CentralArquivista-XBOX360-part1/Assassins Creed 3 (EU) (Rev-1) - Disc-2.iso"
    },
    {
        "FileName": "Assassins Creed 3 (EU) - Disc-1.iso",
        "Size": "8.14 GB",
        "DownloadLink": "https://archive.org/download/CentralArquivista-XBOX360-part1/Assassins Creed 3 (EU) - Disc-1.iso"
    },
    {
        "FileName": "Assassins Creed 3 (EU) - Disc-2.iso",
        "Size": "8.14 GB",
        "DownloadLink": "https://archive.org/download/CentralArquivista-XBOX360-part1/Assassins Creed 3 (EU) - Disc-2.iso"
    }
]